odoo/addons/account_multicompany_easy_creation/README.rst
odoo/addons/account_multicompany_easy_creation/__init__.py
odoo/addons/account_multicompany_easy_creation/__manifest__.py
odoo/addons/account_multicompany_easy_creation/i18n/account_multicompany_easy_creation.pot
odoo/addons/account_multicompany_easy_creation/i18n/es.po
odoo/addons/account_multicompany_easy_creation/static/description/icon.png
odoo/addons/account_multicompany_easy_creation/wizards/__init__.py
odoo/addons/account_multicompany_easy_creation/wizards/multicompany_easy_creation.py
odoo/addons/account_multicompany_easy_creation/wizards/multicompany_easy_creation.xml
odoo11_addon_account_multicompany_easy_creation-11.0.1.0.1.dist-info/METADATA
odoo11_addon_account_multicompany_easy_creation-11.0.1.0.1.dist-info/WHEEL
odoo11_addon_account_multicompany_easy_creation-11.0.1.0.1.dist-info/top_level.txt
odoo11_addon_account_multicompany_easy_creation-11.0.1.0.1.dist-info/RECORD
